flask_commands/__init__.py
flask_commands/cli.py
flask_commands/commands/controller.py
flask_commands/commands/form.py
flask_commands/commands/model.py
flask_commands/commands/new.py
flask_commands/commands/route.py
flask_commands/commands/view.py
flask_commands/project/.env
flask_commands/project/.env.example
flask_commands/project/app/__init__.py
flask_commands/project/app/controllers/__init__.py
flask_commands/project/app/controllers/main_controller.py
flask_commands/project/app/models/__init__.py
flask_commands/project/app/models/user.py
flask_commands/project/app/routes/mains/__init__.py
flask_commands/project/app/routes/mains/routes.py
flask_commands/project/app/static/src/input.css
flask_commands/project/app/templates/mains/index.html
flask_commands/project/config/__init__.py
flask_commands/project/config/base_config.py
flask_commands/project/config/development_config.py
flask_commands/project/config/production_config.py
flask_commands/project/run.py
flask_commands/project/run.sh
flask_commands/utils/__init__.py
flask_commands/utils/controllers.py
flask_commands/utils/css.py
flask_commands/utils/databases.py
flask_commands/utils/files.py
flask_commands/utils/models.py
flask_commands/utils/naming.py
flask_commands/utils/routes.py
flask_commands/utils/scaffold.py
flask_commands/utils/venv.py
flask_commands/utils/views.py
flask_commands/utils/wirings.py
flask_commands-0.2.4.dist-info/METADATA
flask_commands-0.2.4.dist-info/WHEEL
flask_commands-0.2.4.dist-info/entry_points.txt
flask_commands-0.2.4.dist-info/licenses/LICENSE
flask_commands-0.2.4.dist-info/RECORD
