Metadata-Version: 2.4
Name: flask-commands
Version: 0.2.4
Summary: A set of command line tools that help you scaffold out your flask application quickly.
License: MIT
License-File: LICENSE
Author: Drew Butcher
Author-email: drewlbutcher@gmail.com
Requires-Python: >=3.10
Classifier: License :: OSI Approved :: MIT License
Classifier: Programming Language :: Python :: 3
Classifier: Programming Language :: Python :: 3.10
Classifier: Programming Language :: Python :: 3.11
Classifier: Programming Language :: Python :: 3.12
Classifier: Programming Language :: Python :: 3.13
Classifier: Programming Language :: Python :: 3.14
Provides-Extra: docs
Requires-Dist: click (>=8.3.1,<9.0.0)
Requires-Dist: sphinx (<9) ; extra == "docs"
Requires-Dist: sphinx-copybutton ; extra == "docs"
Project-URL: Homepage, https://flask-commands.readthedocs.io/en/latest/
Project-URL: Issues, https://github.com/drewbutcher/flask-commands/issues
Project-URL: Repository, https://github.com/drewbutcher/flask-commands
